forement/__init__.py
forement/forement.py
forement/sam.py
forement/unsupervised.py
forement-0.0.1.dist-info/LICENSE
forement-0.0.1.dist-info/METADATA
forement-0.0.1.dist-info/WHEEL
forement-0.0.1.dist-info/top_level.txt
forement-0.0.1.dist-info/RECORD
