Metadata-Version: 2.1
Name: forement
Version: 0.0.1
Summary: A collection of unsupervised clustering tools for foreground segmentation
Author-email: Brandon Hastings <bhastings23320@gmail.com>
License: MIT License
Project-URL: Homepage, https://github.com/brandon-hastings/forement
Keywords: foreground segmentation,color clustering
Classifier: Programming Language :: Python
Requires-Python: >=3.10
License-File: LICENSE
Requires-Dist: ultralytics>=8.2.82
Requires-Dist: opencv-python>=4.10.0.84
Requires-Dist: orchard-bouman>=1.0.1
